bitcoin_notifier_rajatbhatt500
